vllm_top/__init__.py
vllm_top/main.py
vllm_top/monitor.py
vllm_top-0.1.2.dist-info/licenses/LICENSE
vllm_top-0.1.2.dist-info/METADATA
vllm_top-0.1.2.dist-info/WHEEL
vllm_top-0.1.2.dist-info/entry_points.txt
vllm_top-0.1.2.dist-info/top_level.txt
vllm_top-0.1.2.dist-info/RECORD
