Metadata-Version: 2.4
Name: vllm-top
Version: 0.1.2
Summary: A monitoring tool for vLLM metrics.
Author-email: Yeok Tatt Cheah <yeokch@gmail.com>
License: MIT
Project-URL: Homepage, https://github.com/yeok-c/vllm-top
Project-URL: Documentation, https://github.com/yeok-c/vllm-top#readme
Project-URL: Repository, https://github.com/yeok-c/vllm-top
Project-URL: Issues, https://github.com/yeok-c/vllm-top/issues
Keywords: vllm,monitoring,metrics
Classifier: Programming Language :: Python :: 3
Classifier: License :: OSI Approved :: MIT License
Classifier: Operating System :: OS Independent
Requires-Python: >=3.6
License-File: LICENSE
Requires-Dist: requests
Requires-Dist: prometheus_client
Dynamic: license-file
